{
  "slug": "365cms-core",
  "name": "365CMS",
  "type": "core",
  "version": "2.7.371",
  "min_php": "8.4",
  "released": "2026-03-27",
  "download_url": "",
  "changelog_url": "https://raw.githubusercontent.com/PS-easyIT/365CMS.DE/main/Changelog.md",
  "checksum_sha256": "",
  "notes": "Release 2.7.371: Die Medienverwaltung erklärt unveränderte Settings-Saves verständlicher, die Benutzerverwaltung staffelt Save-Fehler robuster und die Gruppenverwaltung öffnet Modale sowie Submit-/Delete-Flows zuverlässiger.",
  "critical": false
}
